django-discard/__init__.py
django-discard/models.py
django_discard/__init__.py
django_discard/models.py
django_discard-0.0.3.dist-info/METADATA
django_discard-0.0.3.dist-info/RECORD
django_discard-0.0.3.dist-info/WHEEL
django_discard-0.0.3.dist-info/top_level.txt
